h3lis200dl.py
circuitpython_h3lis200dl-0.2.0.dist-info/LICENSE
circuitpython_h3lis200dl-0.2.0.dist-info/METADATA
circuitpython_h3lis200dl-0.2.0.dist-info/WHEEL
circuitpython_h3lis200dl-0.2.0.dist-info/top_level.txt
circuitpython_h3lis200dl-0.2.0.dist-info/RECORD
