Metadata-Version: 2.1
Name: circuitpython-h3lis200dl
Version: 0.2.0
Summary: CircuitPython Driver for the ST H3LIS200DL Accelerometer
Author-email: JDM <xxx@mailmeto.mozmail.com>
License: MIT
Project-URL: Homepage, https://github.com/jposada202020/CircuitPython_H3LIS200DL
Keywords: sensor,blinka,circuitpython,micropython,h3lis200dl,acceleration,driver,H3LIS200DL,sensor
Classifier: Intended Audience :: Developers
Classifier: Topic :: Software Development :: Libraries
Classifier: Topic :: Software Development :: Embedded Systems
Classifier: Topic :: System :: Hardware
Classifier: License :: OSI Approved :: MIT License
Classifier: Programming Language :: Python :: 3
License-File: LICENSE
Requires-Dist: Adafruit-Blinka
Requires-Dist: adafruit-circuitpython-busdevice
Requires-Dist: adafruit-circuitpython-register
Provides-Extra: optional
